[{"from":"miyakita5185","unixTime":"1738212264598","latitude":"37.8672517","longitude":"138.9393967","imageLength":"0"},
{"from":"miyakita5185","unixTime":"1738212267233","latitude":"37.8672517","longitude":"138.9393967","imageLength":"0"},
{"from":"miyakita5185","unixTime":"1738212270214","latitude":"37.8672517","longitude":"138.9393967","imageLength":"0"},
{"from":"miyakita5185","unixTime":"1738212273225","latitude":"37.8671551","longitude":"138.9393693","imageLength":"0"},
{"from":"miyakita5185","unixTime":"1738212276228","latitude":"37.867143","longitude":"138.9393505","imageLength":"0"},
{"from":"miyakita5185","unixTime":"1738212279218","latitude":"37.8672317","longitude":"138.9393476","imageLength":"0"},
{"from":"miyakita5185","unixTime":"1738212282230","latitude":"37.8672333","longitude":"138.9393483","imageLength":"0"},
{"from":"miyakita5185","unixTime":"1738212285230","latitude":"37.8672333","longitude":"138.9393483","imageLength":"0"},
{"from":"miyakita5185","unixTime":"1738212288222","latitude":"37.8672333","longitude":"138.9393483","imageLength":"0"},
{"from":"miyakita5185","unixTime":"1738212291228","latitude":"37.8672333","longitude":"138.9393483","imageLength":"0"},
{"from":"miyakita5185","unixTime":"1738212294222","latitude":"37.8672333","longitude":"138.9393483","imageLength":"0"}]