[{"from":"miyakita4406","unixTime":"1738732730047","latitude":"37.8669832","longitude":"138.9395743","imageLength":"1"},
{"from":"miyakita4406","unixTime":"1738732733041","latitude":"37.8669807","longitude":"138.9395884","imageLength":"1"},
{"from":"miyakita4406","unixTime":"1738732735924","latitude":"37.8669756","longitude":"138.9395933","imageLength":"1"},
{"from":"miyakita4406","unixTime":"1738732738055","latitude":"37.866975","longitude":"138.9395933","imageLength":"1"},
{"from":"miyakita4406","unixTime":"1738732741052","latitude":"37.8670267","longitude":"138.9395804","imageLength":"1"},
{"from":"miyakita4406","unixTime":"1738732744050","latitude":"37.8670264","longitude":"138.9395877","imageLength":"1"},
{"from":"miyakita4406","unixTime":"1738732747045","latitude":"37.8670321","longitude":"138.9395871","imageLength":"1"},
{"from":"miyakita4406","unixTime":"1738732750046","latitude":"37.867036","longitude":"138.9395879","imageLength":"1"},
{"from":"miyakita4406","unixTime":"1738732753046","latitude":"37.8670009","longitude":"138.9396013","imageLength":"1"},
{"from":"miyakita4406","unixTime":"1738732756047","latitude":"37.8669973","longitude":"138.9396057","imageLength":"1"},
{"from":"miyakita4406","unixTime":"1738732759043","latitude":"37.8670108","longitude":"138.9396082","imageLength":"1"}]