[{"from":"miyakita6185","unixTime":"1737947855364","latitude":"37.8642084","longitude":"138.9383346","imageLength":"0"},
{"from":"miyakita6185","unixTime":"1737947858362","latitude":"37.864214","longitude":"138.9383482","imageLength":"0"},
{"from":"miyakita6185","unixTime":"1737947861360","latitude":"37.8642971","longitude":"138.9383357","imageLength":"0"},
{"from":"miyakita6185","unixTime":"1737947864364","latitude":"37.8643484","longitude":"138.9383244","imageLength":"0"},
{"from":"miyakita6185","unixTime":"1737947867369","latitude":"37.8642956","longitude":"138.938327","imageLength":"0"},
{"from":"miyakita6185","unixTime":"1737947870365","latitude":"37.8642383","longitude":"138.9383321","imageLength":"0"},
{"from":"miyakita6185","unixTime":"1737947873370","latitude":"37.8642143","longitude":"138.9383595","imageLength":"0"},
{"from":"miyakita6185","unixTime":"1737947876361","latitude":"37.8641376","longitude":"138.9384241","imageLength":"0"},
{"from":"miyakita6185","unixTime":"1737947879365","latitude":"37.8640845","longitude":"138.9384775","imageLength":"0"},
{"from":"miyakita6185","unixTime":"1737947882355","latitude":"37.8640093","longitude":"138.9384712","imageLength":"0"},
{"from":"miyakita6185","unixTime":"1737947885367","latitude":"37.8639649","longitude":"138.9384868","imageLength":"0"}]