[{"from":"miyakita4428","unixTime":"1738731345098","latitude":"37.8668436","longitude":"138.939626","imageLength":"1"},
{"from":"miyakita4428","unixTime":"1738731348116","latitude":"37.8668323","longitude":"138.9395838","imageLength":"1"},
{"from":"miyakita4428","unixTime":"1738731350485","latitude":"37.8668286","longitude":"138.9395735","imageLength":"1"},
{"from":"miyakita4428","unixTime":"1738731353113","latitude":"37.866826","longitude":"138.9395567","imageLength":"1"},
{"from":"miyakita4428","unixTime":"1738731356097","latitude":"37.8668269","longitude":"138.9395468","imageLength":"1"},
{"from":"miyakita4428","unixTime":"1738731359101","latitude":"37.8668312","longitude":"138.9395182","imageLength":"1"},
{"from":"miyakita4428","unixTime":"1738731362092","latitude":"37.8668332","longitude":"138.939503","imageLength":"1"},
{"from":"miyakita4428","unixTime":"1738731365099","latitude":"37.8668397","longitude":"138.9394798","imageLength":"1"},
{"from":"miyakita4428","unixTime":"1738731368104","latitude":"37.8669353","longitude":"138.9393703","imageLength":"1"},
{"from":"miyakita4428","unixTime":"1738731371093","latitude":"37.8669693","longitude":"138.9393499","imageLength":"1"},
{"from":"miyakita4428","unixTime":"1738731374108","latitude":"37.8669731","longitude":"138.9393541","imageLength":"1"}]