[{"from":"miyakita756","unixTime":"1738296760288","latitude":"37.8680883","longitude":"138.9383783","imageLength":"0"},
{"from":"miyakita756","unixTime":"1738296763292","latitude":"37.8680883","longitude":"138.9383783","imageLength":"0"},
{"from":"miyakita756","unixTime":"1738296766283","latitude":"37.8680883","longitude":"138.9383783","imageLength":"0"},
{"from":"miyakita756","unixTime":"1738296769278","latitude":"37.8680883","longitude":"138.9383783","imageLength":"0"},
{"from":"miyakita756","unixTime":"1738296772289","latitude":"37.8680883","longitude":"138.9383783","imageLength":"0"},
{"from":"miyakita756","unixTime":"1738296775293","latitude":"37.8680883","longitude":"138.9383783","imageLength":"0"},
{"from":"miyakita756","unixTime":"1738296778284","latitude":"37.8680883","longitude":"138.9383783","imageLength":"0"},
{"from":"miyakita756","unixTime":"1738296781297","latitude":"37.8680883","longitude":"138.9383783","imageLength":"0"},
{"from":"miyakita756","unixTime":"1738296784291","latitude":"37.8680883","longitude":"138.9383783","imageLength":"0"},
{"from":"miyakita756","unixTime":"1738296787291","latitude":"37.8680883","longitude":"138.9383783","imageLength":"0"},
{"from":"miyakita756","unixTime":"1738296790288","latitude":"37.8680883","longitude":"138.9383783","imageLength":"0"}]