[{"from":"miyakita5867","unixTime":"1738210246562","latitude":"37.8681597","longitude":"138.9383692","imageLength":"0"},
{"from":"miyakita5867","unixTime":"1738210251628","latitude":"37.8681537","longitude":"138.9383751","imageLength":"0"},
{"from":"miyakita5867","unixTime":"1738210256654","latitude":"37.8681508","longitude":"138.9383748","imageLength":"0"},
{"from":"miyakita5867","unixTime":"1738210261694","latitude":"37.8681516","longitude":"138.9383802","imageLength":"0"},
{"from":"miyakita5867","unixTime":"1738210266739","latitude":"37.8681521","longitude":"138.9383797","imageLength":"0"},
{"from":"miyakita5867","unixTime":"1738210271805","latitude":"37.8681547","longitude":"138.9383697","imageLength":"0"},
{"from":"miyakita5867","unixTime":"1738210276803","latitude":"37.868155","longitude":"138.9383679","imageLength":"0"},
{"from":"miyakita5867","unixTime":"1738210281835","latitude":"37.8681514","longitude":"138.9383805","imageLength":"0"},
{"from":"miyakita5867","unixTime":"1738210286785","latitude":"37.8681461","longitude":"138.9383885","imageLength":"0"},
{"from":"miyakita5867","unixTime":"1738210291857","latitude":"37.8681517","longitude":"138.9383753","imageLength":"0"},
{"from":"miyakita5867","unixTime":"1738210296842","latitude":"37.8681476","longitude":"138.9383882","imageLength":"0"}]