[{"from":"miyakita789","unixTime":"1738728411333","latitude":"37.8629467","longitude":"138.9404117","imageLength":"1"},
{"from":"miyakita789","unixTime":"1738728414334","latitude":"37.8629467","longitude":"138.9404117","imageLength":"1"},
{"from":"miyakita789","unixTime":"1738728417340","latitude":"37.8629467","longitude":"138.9404117","imageLength":"1"},
{"from":"miyakita789","unixTime":"1738728420332","latitude":"37.8629541","longitude":"138.9403618","imageLength":"1"},
{"from":"miyakita789","unixTime":"1738728423342","latitude":"37.8629648","longitude":"138.9403534","imageLength":"1"},
{"from":"miyakita789","unixTime":"1738728426344","latitude":"37.862965","longitude":"138.9403533","imageLength":"1"},
{"from":"miyakita789","unixTime":"1738728429338","latitude":"37.862965","longitude":"138.9403533","imageLength":"1"},
{"from":"miyakita789","unixTime":"1738728432338","latitude":"37.8629914","longitude":"138.9403175","imageLength":"1"},
{"from":"miyakita789","unixTime":"1738728435340","latitude":"37.8629983","longitude":"138.94031","imageLength":"1"},
{"from":"miyakita789","unixTime":"1738728438342","latitude":"37.8629983","longitude":"138.94031","imageLength":"1"},
{"from":"miyakita789","unixTime":"1738728441321","latitude":"37.8629983","longitude":"138.94031","imageLength":"1"}]