[{"from":"miyakita6859","unixTime":"1738119732120","latitude":"37.8671425","longitude":"138.9392093","imageLength":"1"},
{"from":"miyakita6859","unixTime":"1738119737119","latitude":"37.8671916","longitude":"138.9391195","imageLength":"1"},
{"from":"miyakita6859","unixTime":"1738119741623","latitude":"37.8670185","longitude":"138.9391765","imageLength":"1"},
{"from":"miyakita6859","unixTime":"1738119744025","latitude":"37.8670036","longitude":"138.9391853","imageLength":"1"},
{"from":"miyakita6859","unixTime":"1738119748294","latitude":"37.8669414","longitude":"138.9392127","imageLength":"1"},
{"from":"miyakita6859","unixTime":"1738119751120","latitude":"37.8670634","longitude":"138.939175","imageLength":"1"},
{"from":"miyakita6859","unixTime":"1738119754015","latitude":"37.8670732","longitude":"138.9391707","imageLength":"1"},
{"from":"miyakita6859","unixTime":"1738119756120","latitude":"37.8669911","longitude":"138.9391776","imageLength":"1"},
{"from":"miyakita6859","unixTime":"1738119761119","latitude":"37.8669425","longitude":"138.9391938","imageLength":"1"},
{"from":"miyakita6859","unixTime":"1738119763946","latitude":"37.8669401","longitude":"138.9391949","imageLength":"1"},
{"from":"miyakita6859","unixTime":"1738119766123","latitude":"37.86694","longitude":"138.939195","imageLength":"1"}]