[{"from":"miyakita3695","unixTime":"1738814989437","latitude":"37.8668367","longitude":"138.93938","imageLength":"1"},
{"from":"miyakita3695","unixTime":"1738814991920","latitude":"37.8668592","longitude":"138.9393406","imageLength":"1"},
{"from":"miyakita3695","unixTime":"1738814994914","latitude":"37.8668376","longitude":"138.9393296","imageLength":"1"},
{"from":"miyakita3695","unixTime":"1738814997922","latitude":"37.8668284","longitude":"138.9393267","imageLength":"1"},
{"from":"miyakita3695","unixTime":"1738815000914","latitude":"37.8668283","longitude":"138.9393267","imageLength":"1"},
{"from":"miyakita3695","unixTime":"1738815003924","latitude":"37.8667423","longitude":"138.9393379","imageLength":"1"},
{"from":"miyakita3695","unixTime":"1738815006923","latitude":"37.8667109","longitude":"138.9393464","imageLength":"1"},
{"from":"miyakita3695","unixTime":"1738815009929","latitude":"37.8667067","longitude":"138.9393483","imageLength":"1"},
{"from":"miyakita3695","unixTime":"1738815012922","latitude":"37.8666979","longitude":"138.9393427","imageLength":"1"},
{"from":"miyakita3695","unixTime":"1738815015921","latitude":"37.8667222","longitude":"138.9393303","imageLength":"1"},
{"from":"miyakita3695","unixTime":"1738815018915","latitude":"37.866735","longitude":"138.9393333","imageLength":"1"}]