[{"from":"miyakita3695","unixTime":"1738820640245","latitude":"37.8668823","longitude":"138.939955","imageLength":"1"},
{"from":"miyakita3695","unixTime":"1738820642764","latitude":"37.86673","longitude":"138.9401066","imageLength":"1"},
{"from":"miyakita3695","unixTime":"1738820645329","latitude":"37.8666066","longitude":"138.9401703","imageLength":"1"},
{"from":"miyakita3695","unixTime":"1738820647822","latitude":"37.8665787","longitude":"138.9401562","imageLength":"1"},
{"from":"miyakita3695","unixTime":"1738820650264","latitude":"37.8668037","longitude":"138.9397826","imageLength":"1"},
{"from":"miyakita3695","unixTime":"1738820652823","latitude":"37.8668946","longitude":"138.9396552","imageLength":"1"},
{"from":"miyakita3695","unixTime":"1738820655486","latitude":"37.8668254","longitude":"138.9395307","imageLength":"1"},
{"from":"miyakita3695","unixTime":"1738820658096","latitude":"37.8668017","longitude":"138.9395034","imageLength":"1"},
{"from":"miyakita3695","unixTime":"1738820660656","latitude":"37.8668901","longitude":"138.9394726","imageLength":"1"},
{"from":"miyakita3695","unixTime":"1738820663379","latitude":"37.8669119","longitude":"138.9395049","imageLength":"1"},
{"from":"miyakita3695","unixTime":"1738820666173","latitude":"37.8669419","longitude":"138.9395183","imageLength":"1"}]