[{"from":"miyakita1066","unixTime":"1738214799124","latitude":"37.8631175","longitude":"138.9401662","imageLength":"0"},
{"from":"miyakita1066","unixTime":"1738214804151","latitude":"37.8631496","longitude":"138.9402246","imageLength":"0"},
{"from":"miyakita1066","unixTime":"1738214809123","latitude":"37.8632046","longitude":"138.9402549","imageLength":"0"},
{"from":"miyakita1066","unixTime":"1738214814124","latitude":"37.8632797","longitude":"138.940288","imageLength":"0"},
{"from":"miyakita1066","unixTime":"1738214819123","latitude":"37.8633462","longitude":"138.9403367","imageLength":"0"},
{"from":"miyakita1066","unixTime":"1738214824108","latitude":"37.8634097","longitude":"138.9403543","imageLength":"0"},
{"from":"miyakita1066","unixTime":"1738214829124","latitude":"37.8634616","longitude":"138.9403421","imageLength":"0"},
{"from":"miyakita1066","unixTime":"1738214834126","latitude":"37.8635248","longitude":"138.9403164","imageLength":"0"},
{"from":"miyakita1066","unixTime":"1738214839125","latitude":"37.8636067","longitude":"138.9402605","imageLength":"0"},
{"from":"miyakita1066","unixTime":"1738214844112","latitude":"37.8636502","longitude":"138.9402172","imageLength":"0"},
{"from":"miyakita1066","unixTime":"1738214849127","latitude":"37.8637182","longitude":"138.9401375","imageLength":"0"}]