[{"from":"miyakita2744","unixTime":"1738124535474","latitude":"37.8682407","longitude":"138.9385558","imageLength":"0"},
{"from":"miyakita2744","unixTime":"1738124538472","latitude":"37.86824","longitude":"138.9385569","imageLength":"0"},
{"from":"miyakita2744","unixTime":"1738124541461","latitude":"37.8682524","longitude":"138.9385624","imageLength":"0"},
{"from":"miyakita2744","unixTime":"1738124544463","latitude":"37.8682562","longitude":"138.9385439","imageLength":"0"},
{"from":"miyakita2744","unixTime":"1738124548504","latitude":"37.8682591","longitude":"138.9385395","imageLength":"0"},
{"from":"miyakita2744","unixTime":"1738124550950","latitude":"37.8682596","longitude":"138.9385378","imageLength":"0"},
{"from":"miyakita2744","unixTime":"1738124553436","latitude":"37.8682594","longitude":"138.9385391","imageLength":"0"},
{"from":"miyakita2744","unixTime":"1738124555719","latitude":"37.8682621","longitude":"138.9385441","imageLength":"0"},
{"from":"miyakita2744","unixTime":"1738124558648","latitude":"37.8682694","longitude":"138.9385299","imageLength":"0"},
{"from":"miyakita2744","unixTime":"1738124561019","latitude":"37.8682424","longitude":"138.9384787","imageLength":"0"},
{"from":"miyakita2744","unixTime":"1738124563546","latitude":"37.8682369","longitude":"138.9384541","imageLength":"0"}]