[{"from":"miyakita4082","unixTime":"1738039602116","latitude":"37.866277","longitude":"138.9392347","imageLength":"33"},
{"from":"miyakita4082","unixTime":"1738039607116","latitude":"37.866146","longitude":"138.9391523","imageLength":"33"},
{"from":"miyakita4082","unixTime":"1738039612116","latitude":"37.8660595","longitude":"138.9391078","imageLength":"33"},
{"from":"miyakita4082","unixTime":"1738039617117","latitude":"37.866247","longitude":"138.9391533","imageLength":"33"},
{"from":"miyakita4082","unixTime":"1738039622116","latitude":"37.8662983","longitude":"138.9391675","imageLength":"33"},
{"from":"miyakita4082","unixTime":"1738039627114","latitude":"37.8664777","longitude":"138.9392246","imageLength":"33"},
{"from":"miyakita4082","unixTime":"1738039632114","latitude":"37.8665628","longitude":"138.9392763","imageLength":"33"},
{"from":"miyakita4082","unixTime":"1738039637115","latitude":"37.8665638","longitude":"138.939286","imageLength":"33"},
{"from":"miyakita4082","unixTime":"1738039642113","latitude":"37.8666862","longitude":"138.9393579","imageLength":"33"},
{"from":"miyakita4082","unixTime":"1738039647115","latitude":"37.8668094","longitude":"138.9393854","imageLength":"33"},
{"from":"miyakita4082","unixTime":"1738039652115","latitude":"37.866876","longitude":"138.9393935","imageLength":"33"}]