[{"from":"miyakita6975","unixTime":"1738038874968","latitude":"37.8668533","longitude":"138.9423933","imageLength":"0"},
{"from":"miyakita6975","unixTime":"1738038877965","latitude":"37.8668533","longitude":"138.9423933","imageLength":"0"},
{"from":"miyakita6975","unixTime":"1738038880979","latitude":"37.8668533","longitude":"138.9423933","imageLength":"0"},
{"from":"miyakita6975","unixTime":"1738038883973","latitude":"37.8668533","longitude":"138.9423933","imageLength":"0"},
{"from":"miyakita6975","unixTime":"1738038886969","latitude":"37.8668533","longitude":"138.9423933","imageLength":"0"},
{"from":"miyakita6975","unixTime":"1738038889972","latitude":"37.8668533","longitude":"138.9423933","imageLength":"0"},
{"from":"miyakita6975","unixTime":"1738038892983","latitude":"37.8668533","longitude":"138.9423933","imageLength":"0"},
{"from":"miyakita6975","unixTime":"1738038895986","latitude":"37.8668533","longitude":"138.9423933","imageLength":"0"},
{"from":"miyakita6975","unixTime":"1738038898972","latitude":"37.8668533","longitude":"138.9423933","imageLength":"0"},
{"from":"miyakita6975","unixTime":"1738038901973","latitude":"37.8668533","longitude":"138.9423933","imageLength":"0"},
{"from":"miyakita6975","unixTime":"1738038905010","latitude":"37.8668533","longitude":"138.9423933","imageLength":"0"}]