[{"from":"miyakita6247","unixTime":"1738212855203","latitude":"37.8670584","longitude":"138.939302","imageLength":"0"},
{"from":"miyakita6247","unixTime":"1738212858199","latitude":"37.8670567","longitude":"138.9393033","imageLength":"0"},
{"from":"miyakita6247","unixTime":"1738212860916","latitude":"37.8670891","longitude":"138.939308","imageLength":"0"},
{"from":"miyakita6247","unixTime":"1738212863201","latitude":"37.8670881","longitude":"138.9393179","imageLength":"0"},
{"from":"miyakita6247","unixTime":"1738212866186","latitude":"37.8670883","longitude":"138.9393183","imageLength":"0"},
{"from":"miyakita6247","unixTime":"1738212869194","latitude":"37.8670883","longitude":"138.9393183","imageLength":"0"},
{"from":"miyakita6247","unixTime":"1738212872191","latitude":"37.8670883","longitude":"138.9393183","imageLength":"0"},
{"from":"miyakita6247","unixTime":"1738212875195","latitude":"37.8670883","longitude":"138.9393183","imageLength":"0"},
{"from":"miyakita6247","unixTime":"1738212878223","latitude":"37.8670883","longitude":"138.9393183","imageLength":"0"},
{"from":"miyakita6247","unixTime":"1738212881043","latitude":"37.8670883","longitude":"138.9393183","imageLength":"0"},
{"from":"miyakita6247","unixTime":"1738212883198","latitude":"37.8670883","longitude":"138.9393183","imageLength":"0"}]