[{"from":"miyakita6247","unixTime":"1738212546162","latitude":"37.8660054","longitude":"138.9413818","imageLength":"0"},
{"from":"miyakita6247","unixTime":"1738212548424","latitude":"37.8660112","longitude":"138.9413543","imageLength":"0"},
{"from":"miyakita6247","unixTime":"1738212550740","latitude":"37.8660184","longitude":"138.9413154","imageLength":"0"},
{"from":"miyakita6247","unixTime":"1738212553092","latitude":"37.8660275","longitude":"138.941281","imageLength":"0"},
{"from":"miyakita6247","unixTime":"1738212555368","latitude":"37.8660375","longitude":"138.9412377","imageLength":"0"},
{"from":"miyakita6247","unixTime":"1738212557677","latitude":"37.8660472","longitude":"138.9411933","imageLength":"0"},
{"from":"miyakita6247","unixTime":"1738212560249","latitude":"37.8660561","longitude":"138.941131","imageLength":"0"},
{"from":"miyakita6247","unixTime":"1738212562606","latitude":"37.8660744","longitude":"138.941061","imageLength":"0"},
{"from":"miyakita6247","unixTime":"1738212565000","latitude":"37.8660992","longitude":"138.94101","imageLength":"0"},
{"from":"miyakita6247","unixTime":"1738212567323","latitude":"37.8661117","longitude":"138.9409527","imageLength":"0"},
{"from":"miyakita6247","unixTime":"1738212569781","latitude":"37.8661094","longitude":"138.9409028","imageLength":"0"}]