[{"from":"miyakita6882","unixTime":"1738811104533","latitude":"37.8667071","longitude":"138.9393992","imageLength":"1"},
{"from":"miyakita6882","to":"error","event":"endpointLost","unixTime":1738811106604},
{"from":"miyakita6882","to":"error","event":"endpointLost","unixTime":1738811106605},
{"from":"miyakita6882","to":"error","event":"endpointLost","unixTime":1738811106626},
{"from":"miyakita6882","to":"error","event":"endpointLost","unixTime":1738811106627},
{"from":"miyakita6882","to":"error","event":"endpointLost","unixTime":1738811106627},
{"from":"miyakita6882","to":"error","event":"endpointLost","unixTime":1738811106628},
{"from":"miyakita6882","unixTime":"1738811107528","latitude":"37.8666908","longitude":"138.9394114","imageLength":"1"},
{"from":"miyakita6882","unixTime":"1738811110521","latitude":"37.8666686","longitude":"138.9394257","imageLength":"1"},
{"from":"miyakita6882","unixTime":"1738811113327","latitude":"37.8666553","longitude":"138.9394364","imageLength":"1"},
{"from":"miyakita6882","unixTime":"1738811115524","latitude":"37.8666133","longitude":"138.9394462","imageLength":"1"}]