[{"from":"miyakita6882","unixTime":"1738817665535","latitude":"37.8637267","longitude":"138.9363883","imageLength":"1"},
{"from":"miyakita6882","unixTime":"1738817668539","latitude":"37.8637267","longitude":"138.9363883","imageLength":"1"},
{"from":"miyakita6882","unixTime":"1738817671536","latitude":"37.8637267","longitude":"138.9363883","imageLength":"1"},
{"from":"miyakita6882","unixTime":"1738817674534","latitude":"37.8637267","longitude":"138.9363883","imageLength":"1"},
{"from":"miyakita6882","unixTime":"1738817677540","latitude":"37.8637267","longitude":"138.9363883","imageLength":"1"},
{"from":"miyakita6882","unixTime":"1738817680530","latitude":"37.8637267","longitude":"138.9363883","imageLength":"1"},
{"from":"miyakita6882","unixTime":"1738817683530","latitude":"37.8637267","longitude":"138.9363883","imageLength":"1"},
{"from":"miyakita6882","unixTime":"1738817686538","latitude":"37.8637267","longitude":"138.9363883","imageLength":"1"},
{"from":"miyakita6882","unixTime":"1738817689535","latitude":"37.8637267","longitude":"138.9363883","imageLength":"1"},
{"from":"miyakita6882","unixTime":"1738817692538","latitude":"37.8637267","longitude":"138.9363883","imageLength":"1"},
{"from":"miyakita6882","unixTime":"1738817695544","latitude":"37.8637267","longitude":"138.9363883","imageLength":"1"}]