[{"from":"miyakita3455","unixTime":"1738033456074","latitude":"37.8668005","longitude":"138.9393903","imageLength":"6"},
{"from":"miyakita3455","unixTime":"1738033459070","latitude":"37.8667662","longitude":"138.9393734","imageLength":"6"},
{"from":"miyakita3455","unixTime":"1738033461776","latitude":"37.8667601","longitude":"138.9393587","imageLength":"6"},
{"from":"miyakita3455","unixTime":"1738033464074","latitude":"37.8667438","longitude":"138.939347","imageLength":"6"},
{"from":"miyakita3455","unixTime":"1738033467074","latitude":"37.8667092","longitude":"138.9393329","imageLength":"6"},
{"from":"miyakita3455","unixTime":"1738033470071","latitude":"37.8667185","longitude":"138.9393255","imageLength":"6"},
{"from":"miyakita3455","unixTime":"1738033473071","latitude":"37.8666788","longitude":"138.9393338","imageLength":"6"},
{"from":"miyakita3455","unixTime":"1738033476079","latitude":"37.8666749","longitude":"138.9393369","imageLength":"6"},
{"from":"miyakita3455","unixTime":"1738033479074","latitude":"37.866665","longitude":"138.939338","imageLength":"6"},
{"from":"miyakita3455","unixTime":"1738033481855","latitude":"37.8666516","longitude":"138.9393352","imageLength":"6"},
{"from":"miyakita3455","to":"error","event":"endpointLost","unixTime":1738033483833}]