[{"from":"miyakita4327","to":"miyakita7286","event":"sendFinish","unixTime":1738129720701},
{"from":"miyakita4327","unixTime":"1738129723011","latitude":"37.8670572","longitude":"138.9389422","imageLength":"1"},
{"from":"miyakita4327","to":"miyakita7286","event":"disconnectTo","unixTime":1738129723345},
{"from":"miyakita4327","to":"miyakita7286","event":"discconected","unixTime":1738129724119},
{"from":"miyakita4327","unixTime":"1738129726025","latitude":"37.8670667","longitude":"138.9390096","imageLength":"1"},
{"from":"miyakita4327","unixTime":"1738129729032","latitude":"37.8670504","longitude":"138.93901","imageLength":"1"},
{"from":"miyakita4327","unixTime":"1738129732010","latitude":"37.8670291","longitude":"138.9389768","imageLength":"1"},
{"from":"miyakita4327","unixTime":"1738129735025","latitude":"37.867025","longitude":"138.9389767","imageLength":"1"},
{"from":"miyakita4327","unixTime":"1738129738022","latitude":"37.867025","longitude":"138.9389767","imageLength":"1"},
{"from":"miyakita4327","unixTime":"1738129741023","latitude":"37.867025","longitude":"138.9389767","imageLength":"1"},
{"from":"miyakita4327","unixTime":"1738129744039","latitude":"37.867025","longitude":"138.9389767","imageLength":"1"}]