[{"from":"miyakita4327","unixTime":"1738128691028","latitude":"37.8669983","longitude":"138.9393617","imageLength":"1"},
{"from":"miyakita4327","unixTime":"1738128694038","latitude":"37.8669983","longitude":"138.9393617","imageLength":"1"},
{"from":"miyakita4327","unixTime":"1738128697020","latitude":"37.8669983","longitude":"138.9393617","imageLength":"1"},
{"from":"miyakita4327","to":"miyakita7286","event":"endpointLost","unixTime":1738128698622},
{"from":"miyakita4327","unixTime":"1738128700034","latitude":"37.8669983","longitude":"138.9393617","imageLength":"1"},
{"from":"miyakita4327","unixTime":"1738128703030","latitude":"37.8669983","longitude":"138.9393617","imageLength":"1"},
{"from":"miyakita4327","unixTime":"1738128706028","latitude":"37.8669983","longitude":"138.9393617","imageLength":"1"},
{"from":"miyakita4327","unixTime":"1738128709032","latitude":"37.8669983","longitude":"138.9393617","imageLength":"1"},
{"from":"miyakita4327","unixTime":"1738128712031","latitude":"37.8669983","longitude":"138.9393617","imageLength":"1"},
{"from":"miyakita4327","unixTime":"1738128715023","latitude":"37.8669983","longitude":"138.9393617","imageLength":"1"},
{"from":"miyakita4327","unixTime":"1738128718014","latitude":"37.8669983","longitude":"138.9393617","imageLength":"1"}]