[{"from":"miyakita4327","to":"miyakita7286","event":"connected","unixTime":1738128289088},
{"from":"miyakita4327","to":"miyakita7286","event":"sendStart","unixTime":1738128289202},
{"from":"miyakita4327","unixTime":"1738128291022","latitude":"37.8670617","longitude":"138.9394883","imageLength":"1"},
{"from":"miyakita4327","unixTime":"1738128294011","latitude":"37.8670617","longitude":"138.9394883","imageLength":"1"},
{"from":"miyakita4327","unixTime":"1738128297043","latitude":"37.8670617","longitude":"138.9394883","imageLength":"1"},
{"from":"miyakita4327","unixTime":"1738128300027","latitude":"37.8670617","longitude":"138.9394883","imageLength":"1"},
{"from":"miyakita4327","unixTime":"1738128303030","latitude":"37.8670617","longitude":"138.9394883","imageLength":"1"},
{"from":"miyakita4327","unixTime":"1738128306048","latitude":"37.8670617","longitude":"138.9394883","imageLength":"1"},
{"from":"miyakita4327","to":"error","event":"endpointLost","unixTime":1738128309025},
{"from":"miyakita4327","to":"miyakita7286","event":"endpointLost","unixTime":1738128309026},
{"from":"miyakita4327","unixTime":"1738128309028","latitude":"37.8670617","longitude":"138.9394883","imageLength":"1"}]