[{"from":"miyakita3126","unixTime":"1738731004239","latitude":"37.863735","longitude":"138.9364183","imageLength":"1"},
{"from":"miyakita3126","unixTime":"1738731007236","latitude":"37.863735","longitude":"138.9364183","imageLength":"1"},
{"from":"miyakita3126","unixTime":"1738731010237","latitude":"37.863735","longitude":"138.9364183","imageLength":"1"},
{"from":"miyakita3126","unixTime":"1738731013243","latitude":"37.863735","longitude":"138.9364183","imageLength":"1"},
{"from":"miyakita3126","unixTime":"1738731016247","latitude":"37.863735","longitude":"138.9364183","imageLength":"1"},
{"from":"miyakita3126","unixTime":"1738731019235","latitude":"37.863735","longitude":"138.9364183","imageLength":"1"},
{"from":"miyakita3126","unixTime":"1738731022244","latitude":"37.863735","longitude":"138.9364183","imageLength":"1"},
{"from":"miyakita3126","unixTime":"1738731025236","latitude":"37.863735","longitude":"138.9364183","imageLength":"1"},
{"from":"miyakita3126","unixTime":"1738731028243","latitude":"37.863735","longitude":"138.9364183","imageLength":"1"},
{"from":"miyakita3126","unixTime":"1738731031237","latitude":"37.863735","longitude":"138.9364183","imageLength":"1"},
{"from":"miyakita3126","unixTime":"1738731034238","latitude":"37.863735","longitude":"138.9364183","imageLength":"1"}]