[{"from":"miyakita3126","unixTime":"1738727927240","latitude":"37.8671389","longitude":"138.9392925","imageLength":"1"},
{"from":"miyakita3126","unixTime":"1738727930246","latitude":"37.8671659","longitude":"138.9393125","imageLength":"1"},
{"from":"miyakita3126","unixTime":"1738727933242","latitude":"37.8671341","longitude":"138.9393237","imageLength":"1"},
{"from":"miyakita3126","unixTime":"1738727935730","latitude":"37.8670803","longitude":"138.939328","imageLength":"1"},
{"from":"miyakita3126","unixTime":"1738727938246","latitude":"37.8671176","longitude":"138.9393299","imageLength":"1"},
{"from":"miyakita3126","unixTime":"1738727941226","latitude":"37.8671988","longitude":"138.9393316","imageLength":"1"},
{"from":"miyakita3126","unixTime":"1738727944242","latitude":"37.8672592","longitude":"138.9393487","imageLength":"1"},
{"from":"miyakita3126","unixTime":"1738727947234","latitude":"37.867308","longitude":"138.9393732","imageLength":"1"},
{"from":"miyakita3126","unixTime":"1738727950242","latitude":"37.8672296","longitude":"138.9393912","imageLength":"1"},
{"from":"miyakita3126","unixTime":"1738727953242","latitude":"37.8672247","longitude":"138.9393763","imageLength":"1"},
{"from":"miyakita3126","unixTime":"1738727955851","latitude":"37.8672185","longitude":"138.9393686","imageLength":"1"}]