[{"from":"miyakita5744","unixTime":"1738296278170","latitude":"37.8659766","longitude":"138.9411564","imageLength":"0"},
{"from":"miyakita5744","unixTime":"1738296280531","latitude":"37.8659747","longitude":"138.9411161","imageLength":"0"},
{"from":"miyakita5744","unixTime":"1738296282915","latitude":"37.865979","longitude":"138.9410743","imageLength":"0"},
{"from":"miyakita5744","unixTime":"1738296285272","latitude":"37.8659814","longitude":"138.9410301","imageLength":"0"},
{"from":"miyakita5744","unixTime":"1738296287613","latitude":"37.8659857","longitude":"138.9409919","imageLength":"0"},
{"from":"miyakita5744","unixTime":"1738296289992","latitude":"37.8659751","longitude":"138.9409502","imageLength":"0"},
{"from":"miyakita5744","unixTime":"1738296292471","latitude":"37.8659685","longitude":"138.9409064","imageLength":"0"},
{"from":"miyakita5744","unixTime":"1738296295004","latitude":"37.8659446","longitude":"138.940867","imageLength":"0"},
{"from":"miyakita5744","unixTime":"1738296297641","latitude":"37.8659265","longitude":"138.9408312","imageLength":"0"},
{"from":"miyakita5744","unixTime":"1738296300061","latitude":"37.8659083","longitude":"138.940795","imageLength":"0"},
{"from":"miyakita5744","unixTime":"1738296302412","latitude":"37.8656924","longitude":"138.9417785","imageLength":"0"}]