[{"from":"miyakita527","unixTime":"1737957158121","latitude":"37.8670565","longitude":"138.9391945","imageLength":"0"},
{"from":"miyakita527","unixTime":"1737957903357","latitude":"37.8670536","longitude":"138.939192","imageLength":"0"},
{"from":"miyakita527","unixTime":"1737957904564","latitude":"37.8669866","longitude":"138.9392187","imageLength":"0"},
{"from":"miyakita527","unixTime":"1737957908425","latitude":"37.8669866","longitude":"138.9392187","imageLength":"0"},
{"from":"miyakita527","unixTime":"1737957913846","latitude":"37.8670039","longitude":"138.9391869","imageLength":"0"},
{"from":"miyakita527","unixTime":"1737957918446","latitude":"37.8670071","longitude":"138.9391853","imageLength":"0"},
{"from":"miyakita527","unixTime":"1737957923847","latitude":"37.867003","longitude":"138.9391826","imageLength":"0"},
{"from":"miyakita527","unixTime":"1737957928474","latitude":"37.867006","longitude":"138.9391887","imageLength":"0"},
{"from":"miyakita527","unixTime":"1737957933861","latitude":"37.8670047","longitude":"138.9391746","imageLength":"0"},
{"from":"miyakita527","unixTime":"1737957938494","latitude":"37.8670067","longitude":"138.9391793","imageLength":"0"},
{"from":"miyakita527","unixTime":"1737957943884","latitude":"37.8669988","longitude":"138.9391987","imageLength":"0"}]