[{"from":"miyakita527","unixTime":"1737956773116","latitude":"37.8668198","longitude":"138.9391876","imageLength":"0"},
{"from":"miyakita527","unixTime":"1737956778111","latitude":"37.8668918","longitude":"138.9392399","imageLength":"0"},
{"from":"miyakita527","unixTime":"1737956783119","latitude":"37.8669361","longitude":"138.9392885","imageLength":"0"},
{"from":"miyakita527","unixTime":"1737956788121","latitude":"37.8668796","longitude":"138.9392744","imageLength":"0"},
{"from":"miyakita527","unixTime":"1737956793125","latitude":"37.866763","longitude":"138.9392354","imageLength":"0"},
{"from":"miyakita527","unixTime":"1737956798119","latitude":"37.8667424","longitude":"138.9392381","imageLength":"0"},
{"from":"miyakita527","unixTime":"1737956803122","latitude":"37.8666765","longitude":"138.9391906","imageLength":"0"},
{"from":"miyakita527","unixTime":"1737956808118","latitude":"37.8667006","longitude":"138.9391964","imageLength":"0"},
{"from":"miyakita527","unixTime":"1737956813116","latitude":"37.866708","longitude":"138.9391934","imageLength":"0"},
{"from":"miyakita527","unixTime":"1737956818118","latitude":"37.8666925","longitude":"138.9391552","imageLength":"0"},
{"from":"miyakita527","unixTime":"1737956823121","latitude":"37.8667012","longitude":"138.9391788","imageLength":"0"}]