[{"from":"miyakita6003","unixTime":"1738216182665","latitude":"37.8669855","longitude":"138.9392677","imageLength":"0"},
{"from":"miyakita6003","unixTime":"1738216187111","latitude":"37.8669875","longitude":"138.9392607","imageLength":"0"},
{"from":"miyakita6003","unixTime":"1738216192673","latitude":"37.8669822","longitude":"138.9392701","imageLength":"0"},
{"from":"miyakita6003","unixTime":"1738216197159","latitude":"37.8669873","longitude":"138.9392608","imageLength":"0"},
{"from":"miyakita6003","unixTime":"1738216202784","latitude":"37.8669849","longitude":"138.9392725","imageLength":"0"},
{"from":"miyakita6003","unixTime":"1738216207216","latitude":"37.8669875","longitude":"138.9392616","imageLength":"0"},
{"from":"miyakita6003","unixTime":"1738216212810","latitude":"37.8669827","longitude":"138.9392662","imageLength":"0"},
{"from":"miyakita6003","unixTime":"1738216217265","latitude":"37.866987","longitude":"138.9392692","imageLength":"0"},
{"from":"miyakita6003","unixTime":"1738216222849","latitude":"37.8669849","longitude":"138.9392734","imageLength":"0"},
{"from":"miyakita6003","unixTime":"1738216227332","latitude":"37.8669934","longitude":"138.9392712","imageLength":"0"},
{"from":"miyakita6003","unixTime":"1738216232911","latitude":"37.8669845","longitude":"138.939258","imageLength":"0"}]