[{"from":"miyakita6003","unixTime":"1738209641272","latitude":"37.8667269","longitude":"138.9393349","imageLength":"1"},
{"from":"miyakita6003","unixTime":"1738209643868","latitude":"37.8667476","longitude":"138.9393187","imageLength":"1"},
{"from":"miyakita6003","unixTime":"1738209646278","latitude":"37.8667693","longitude":"138.9393135","imageLength":"1"},
{"from":"miyakita6003","unixTime":"1738209649283","latitude":"37.8667806","longitude":"138.9393255","imageLength":"1"},
{"from":"miyakita6003","unixTime":"1738209652289","latitude":"37.8667906","longitude":"138.9393104","imageLength":"1"},
{"from":"miyakita6003","unixTime":"1738209655287","latitude":"37.8668124","longitude":"138.9393163","imageLength":"1"},
{"from":"miyakita6003","unixTime":"1738209658288","latitude":"37.8668429","longitude":"138.9393044","imageLength":"1"},
{"from":"miyakita6003","unixTime":"1738209661289","latitude":"37.8668416","longitude":"138.9393047","imageLength":"1"},
{"from":"miyakita6003","unixTime":"1738209663985","latitude":"37.8668417","longitude":"138.9393033","imageLength":"1"},
{"from":"miyakita6003","unixTime":"1738209666302","latitude":"37.8668416","longitude":"138.9393062","imageLength":"1"},
{"from":"miyakita6003","unixTime":"1738209669273","latitude":"37.8668267","longitude":"138.939313","imageLength":"1"}]