[{"from":"miyakita7093","unixTime":"1738297656616","latitude":"37.8638717","longitude":"138.938215","imageLength":"0"},
{"from":"miyakita7093","unixTime":"1738297659629","latitude":"37.8638717","longitude":"138.938215","imageLength":"0"},
{"from":"miyakita7093","unixTime":"1738297662633","latitude":"37.8638717","longitude":"138.938215","imageLength":"0"},
{"from":"miyakita7093","unixTime":"1738297665617","latitude":"37.8638717","longitude":"138.938215","imageLength":"0"},
{"from":"miyakita7093","unixTime":"1738297668617","latitude":"37.8638717","longitude":"138.938215","imageLength":"0"},
{"from":"miyakita7093","unixTime":"1738297671247","latitude":"37.8638717","longitude":"138.938215","imageLength":"0"},
{"from":"miyakita7093","unixTime":"1738297673622","latitude":"37.8638717","longitude":"138.938215","imageLength":"0"},
{"from":"miyakita7093","unixTime":"1738297676625","latitude":"37.8638717","longitude":"138.938215","imageLength":"0"},
{"from":"miyakita7093","unixTime":"1738297679604","latitude":"37.8638717","longitude":"138.938215","imageLength":"0"},
{"from":"miyakita7093","unixTime":"1738297682628","latitude":"37.8638717","longitude":"138.938215","imageLength":"0"},
{"from":"miyakita7093","unixTime":"1738297685617","latitude":"37.8638717","longitude":"138.938215","imageLength":"0"}]