[{"from":"miyakita7093","unixTime":"1738298624607","latitude":"37.8637933","longitude":"138.9381967","imageLength":"0"},
{"from":"miyakita7093","unixTime":"1738298627624","latitude":"37.8637933","longitude":"138.9381967","imageLength":"0"},
{"from":"miyakita7093","unixTime":"1738298630623","latitude":"37.8637933","longitude":"138.9381967","imageLength":"0"},
{"from":"miyakita7093","unixTime":"1738298633625","latitude":"37.8637933","longitude":"138.9381967","imageLength":"0"},
{"from":"miyakita7093","unixTime":"1738298636625","latitude":"37.8637933","longitude":"138.9381967","imageLength":"0"},
{"from":"miyakita7093","unixTime":"1738298639630","latitude":"37.8637933","longitude":"138.9381967","imageLength":"0"},
{"from":"miyakita7093","unixTime":"1738298642624","latitude":"37.8637933","longitude":"138.9381967","imageLength":"0"},
{"from":"miyakita7093","unixTime":"1738298645613","latitude":"37.8637933","longitude":"138.9381967","imageLength":"0"},
{"from":"miyakita7093","unixTime":"1738298648628","latitude":"37.8637933","longitude":"138.9381967","imageLength":"0"},
{"from":"miyakita7093","unixTime":"1738298651624","latitude":"37.8637933","longitude":"138.9381967","imageLength":"0"},
{"from":"miyakita7093","unixTime":"1738298654631","latitude":"37.8637933","longitude":"138.9381967","imageLength":"0"}]