[{"from":"miyakita4812","unixTime":"1738299282400","latitude":"37.8673229","longitude":"138.9394933","imageLength":"0"},
{"from":"miyakita4812","unixTime":"1738299285412","latitude":"37.8674426","longitude":"138.9394572","imageLength":"0"},
{"from":"miyakita4812","unixTime":"1738299288397","latitude":"37.8675006","longitude":"138.9394223","imageLength":"0"},
{"from":"miyakita4812","unixTime":"1738299291401","latitude":"37.8675424","longitude":"138.9394031","imageLength":"0"},
{"from":"miyakita4812","unixTime":"1738299294398","latitude":"37.8675652","longitude":"138.9393723","imageLength":"0"},
{"from":"miyakita4812","unixTime":"1738299297391","latitude":"37.8676054","longitude":"138.9393741","imageLength":"0"},
{"from":"miyakita4812","unixTime":"1738299300392","latitude":"37.8676441","longitude":"138.9393828","imageLength":"0"},
{"from":"miyakita4812","unixTime":"1738299303401","latitude":"37.8676851","longitude":"138.9393855","imageLength":"0"},
{"from":"miyakita4812","unixTime":"1738299306397","latitude":"37.8677275","longitude":"138.939373","imageLength":"0"},
{"from":"miyakita4812","unixTime":"1738299309396","latitude":"37.8677396","longitude":"138.9393739","imageLength":"0"},
{"from":"miyakita4812","unixTime":"1738299312398","latitude":"37.8677457","longitude":"138.9393684","imageLength":"0"}]