[{"from":"miyakita4876","unixTime":"1738129979633","latitude":"37.867382","longitude":"138.9393568","imageLength":"1"},
{"from":"miyakita4876","unixTime":"1738129982566","latitude":"37.8673817","longitude":"138.9393567","imageLength":"1"},
{"from":"miyakita4876","unixTime":"1738129985618","latitude":"37.8673817","longitude":"138.9393567","imageLength":"1"},
{"from":"miyakita4876","unixTime":"1738129988162","latitude":"37.8673817","longitude":"138.9393567","imageLength":"1"},
{"from":"miyakita4876","unixTime":"1738129990626","latitude":"37.8673508","longitude":"138.9393617","imageLength":"1"},
{"from":"miyakita4876","unixTime":"1738129993625","latitude":"37.867332","longitude":"138.9393723","imageLength":"1"},
{"from":"miyakita4876","unixTime":"1738129996624","latitude":"37.8672696","longitude":"138.9393841","imageLength":"1"},
{"from":"miyakita4876","unixTime":"1738129999632","latitude":"37.8672486","longitude":"138.9393941","imageLength":"1"},
{"from":"miyakita4876","unixTime":"1738130002628","latitude":"37.8672111","longitude":"138.9394024","imageLength":"1"},
{"from":"miyakita4876","unixTime":"1738130005623","latitude":"37.867205","longitude":"138.9394165","imageLength":"1"},
{"from":"miyakita4876","unixTime":"1738130008257","latitude":"37.867205","longitude":"138.9394167","imageLength":"1"}]