[{"from":"miyakita4876","unixTime":"1738118685619","latitude":"37.8669815","longitude":"138.9394131","imageLength":"1"},
{"from":"miyakita4876","unixTime":"1738118688623","latitude":"37.8669328","longitude":"138.9393907","imageLength":"1"},
{"from":"miyakita4876","unixTime":"1738118691623","latitude":"37.8668783","longitude":"138.9393832","imageLength":"1"},
{"from":"miyakita4876","unixTime":"1738118694616","latitude":"37.8668626","longitude":"138.9393875","imageLength":"1"},
{"from":"miyakita4876","unixTime":"1738118697631","latitude":"37.8668518","longitude":"138.9393867","imageLength":"1"},
{"from":"miyakita4876","unixTime":"1738118700408","latitude":"37.8668517","longitude":"138.9393867","imageLength":"1"},
{"from":"miyakita4876","unixTime":"1738118702631","latitude":"37.8668517","longitude":"138.9393867","imageLength":"1"},
{"from":"miyakita4876","unixTime":"1738118704967","latitude":"37.8668517","longitude":"138.9393867","imageLength":"1"},
{"from":"miyakita4876","unixTime":"1738118707631","latitude":"37.8668517","longitude":"138.9393867","imageLength":"1"},
{"from":"miyakita4876","unixTime":"1738118710487","latitude":"37.866777","longitude":"138.9394405","imageLength":"1"},
{"from":"miyakita4876","unixTime":"1738118712631","latitude":"37.8667565","longitude":"138.9394419","imageLength":"1"}]