[{"from":"miyakita2146","unixTime":"1738293176544","latitude":"37.8662963","longitude":"138.9395711","imageLength":"1"},
{"from":"miyakita2146","unixTime":"1738293179556","latitude":"37.8662338","longitude":"138.9395572","imageLength":"1"},
{"from":"miyakita2146","unixTime":"1738293182565","latitude":"37.8661679","longitude":"138.9395486","imageLength":"1"},
{"from":"miyakita2146","unixTime":"1738293185557","latitude":"37.8661361","longitude":"138.9395388","imageLength":"1"},
{"from":"miyakita2146","unixTime":"1738293188558","latitude":"37.8661623","longitude":"138.9395419","imageLength":"1"},
{"from":"miyakita2146","unixTime":"1738293191294","latitude":"37.8661456","longitude":"138.9395418","imageLength":"1"},
{"from":"miyakita2146","unixTime":"1738293193553","latitude":"37.8662244","longitude":"138.9395724","imageLength":"1"},
{"from":"miyakita2146","unixTime":"1738293196568","latitude":"37.8662253","longitude":"138.9395654","imageLength":"1"},
{"from":"miyakita2146","unixTime":"1738293199563","latitude":"37.8662417","longitude":"138.9395586","imageLength":"1"},
{"from":"miyakita2146","unixTime":"1738293202561","latitude":"37.8662662","longitude":"138.9395749","imageLength":"1"},
{"from":"miyakita2146","unixTime":"1738293205560","latitude":"37.8663146","longitude":"138.9395842","imageLength":"1"}]